dataopen/__init__.py
dataopen/client.py
dataopen_sdk_python-0.0.7.dist-info/LICENSE
dataopen_sdk_python-0.0.7.dist-info/METADATA
dataopen_sdk_python-0.0.7.dist-info/WHEEL
dataopen_sdk_python-0.0.7.dist-info/top_level.txt
dataopen_sdk_python-0.0.7.dist-info/RECORD
