Metadata-Version: 2.1
Name: dataopen-sdk-python
Version: 0.0.7
Summary: 火山Dataopen python 语言sdk
Home-page: UNKNOWN
Author: caichengnan@bytedance.com
License: Apache-2.0
Platform: UNKNOWN
Requires-Dist: requests (>=2.25)
